// class version 50.0 (50)
// access flags 0x20
class org/apache/zookeeper/ZooKeeper$ExistsWatchRegistration extends org/apache/zookeeper/ZooKeeper$WatchRegistration {

  // compiled from: ZooKeeper.java
  // access flags 0x0
  INNERCLASS org/apache/zookeeper/ZooKeeper$ExistsWatchRegistration org/apache/zookeeper/ZooKeeper ExistsWatchRegistration
  // access flags 0x400
  abstract INNERCLASS org/apache/zookeeper/ZooKeeper$WatchRegistration org/apache/zookeeper/ZooKeeper WatchRegistration
  // access flags 0xA
  private static INNERCLASS org/apache/zookeeper/ZooKeeper$ZKWatchManager org/apache/zookeeper/ZooKeeper ZKWatchManager
  // access flags 0x4019
  public final static enum INNERCLASS org/apache/zookeeper/KeeperException$Code org/apache/zookeeper/KeeperException Code

  // access flags 0x1010
  final synthetic Lorg/apache/zookeeper/ZooKeeper; this$0

  // access flags 0x1
  public <init>(Lorg/apache/zookeeper/ZooKeeper;Lorg/apache/zookeeper/Watcher;Ljava/lang/String;)V
   L0
    LINENUMBER 279 L0
    ALOAD 0
    ALOAD 1
    PUTFIELD org/apache/zookeeper/ZooKeeper$ExistsWatchRegistration.this$0 : Lorg/apache/zookeeper/ZooKeeper;
   L1
    LINENUMBER 280 L1
    ALOAD 0
    ALOAD 1
    ALOAD 2
    ALOAD 3
    INVOKESPECIAL org/apache/zookeeper/ZooKeeper$WatchRegistration.<init> (Lorg/apache/zookeeper/ZooKeeper;Lorg/apache/zookeeper/Watcher;Ljava/lang/String;)V
   L2
    LINENUMBER 281 L2
    RETURN
   L3
    LOCALVARIABLE this Lorg/apache/zookeeper/ZooKeeper$ExistsWatchRegistration; L0 L3 0
    LOCALVARIABLE this$0 Lorg/apache/zookeeper/ZooKeeper; L0 L3 1
    LOCALVARIABLE watcher Lorg/apache/zookeeper/Watcher; L0 L3 2
    LOCALVARIABLE clientPath Ljava/lang/String; L0 L3 3
    MAXSTACK = 4
    MAXLOCALS = 4

  // access flags 0x4
  // signature (I)Ljava/util/Map<Ljava/lang/String;Ljava/util/Set<Lorg/apache/zookeeper/Watcher;>;>;
  // declaration: java.util.Map<java.lang.String, java.util.Set<org.apache.zookeeper.Watcher>> getWatches(int)
  protected getWatches(I)Ljava/util/Map;
   L0
    LINENUMBER 285 L0
    ILOAD 1
    IFNE L1
    ALOAD 0
    GETFIELD org/apache/zookeeper/ZooKeeper$ExistsWatchRegistration.this$0 : Lorg/apache/zookeeper/ZooKeeper;
    INVOKESTATIC org/apache/zookeeper/ZooKeeper.access$500 (Lorg/apache/zookeeper/ZooKeeper;)Lorg/apache/zookeeper/ZooKeeper$ZKWatchManager;
    INVOKESTATIC org/apache/zookeeper/ZooKeeper$ZKWatchManager.access$100 (Lorg/apache/zookeeper/ZooKeeper$ZKWatchManager;)Ljava/util/Map;
    GOTO L2
   L1
   FRAME FULL [org/apache/zookeeper/ZooKeeper$ExistsWatchRegistration I] []
    ALOAD 0
    GETFIELD org/apache/zookeeper/ZooKeeper$ExistsWatchRegistration.this$0 : Lorg/apache/zookeeper/ZooKeeper;
    INVOKESTATIC org/apache/zookeeper/ZooKeeper.access$500 (Lorg/apache/zookeeper/ZooKeeper;)Lorg/apache/zookeeper/ZooKeeper$ZKWatchManager;
    INVOKESTATIC org/apache/zookeeper/ZooKeeper$ZKWatchManager.access$200 (Lorg/apache/zookeeper/ZooKeeper$ZKWatchManager;)Ljava/util/Map;
   L2
   FRAME FULL [org/apache/zookeeper/ZooKeeper$ExistsWatchRegistration I] [java/util/Map]
    ARETURN
   L3
    LOCALVARIABLE this Lorg/apache/zookeeper/ZooKeeper$ExistsWatchRegistration; L0 L3 0
    LOCALVARIABLE rc I L0 L3 1
    MAXSTACK = 1
    MAXLOCALS = 2

  // access flags 0x4
  protected shouldAddWatch(I)Z
   L0
    LINENUMBER 290 L0
    ILOAD 1
    IFEQ L1
    ILOAD 1
    GETSTATIC org/apache/zookeeper/KeeperException$Code.NONODE : Lorg/apache/zookeeper/KeeperException$Code;
    INVOKEVIRTUAL org/apache/zookeeper/KeeperException$Code.intValue ()I
    IF_ICMPNE L2
   L1
   FRAME FULL [org/apache/zookeeper/ZooKeeper$ExistsWatchRegistration I] []
    ICONST_1
    GOTO L3
   L2
   FRAME FULL [org/apache/zookeeper/ZooKeeper$ExistsWatchRegistration I] []
    ICONST_0
   L3
   FRAME FULL [org/apache/zookeeper/ZooKeeper$ExistsWatchRegistration I] [I]
    IRETURN
   L4
    LOCALVARIABLE this Lorg/apache/zookeeper/ZooKeeper$ExistsWatchRegistration; L0 L4 0
    LOCALVARIABLE rc I L0 L4 1
    MAXSTACK = 2
    MAXLOCALS = 2
}

